dockerpyze/__init__.py
dockerpyze/builder.py
dockerpyze/poetry_plugin.py
dockerpyze-2.2.0.dist-info/licenses/LICENSE
dockerpyze-2.2.0.dist-info/METADATA
dockerpyze-2.2.0.dist-info/WHEEL
dockerpyze-2.2.0.dist-info/entry_points.txt
dockerpyze-2.2.0.dist-info/top_level.txt
dockerpyze-2.2.0.dist-info/RECORD
