Metadata-Version: 2.4
Name: dockerpyze
Version: 2.2.0
Summary: Python applications to Docker, automatically.
Author-email: Nicolò Boschi <boschi1997@gmail.com>
Maintainer-email: Nicolò Boschi <boschi1997@gmail.com>
License-Expression: MIT
Project-URL: Homepage, https://github.com/nicoloboschi/dockerpyze
Project-URL: Repository, https://github.com/nicoloboschi/dockerpyze
Project-URL: Documentation, https://github.com/nicoloboschi/dockerpyze
Keywords: poetry,packaging,docker,uv
Classifier: Intended Audience :: Developers
Classifier: Intended Audience :: Information Technology
Classifier: Intended Audience :: System Administrators
Classifier: Operating System :: OS Independent
Classifier: Programming Language :: Python
Classifier: Programming Language :: Python :: 3
Classifier: Topic :: Software Development
Classifier: Topic :: Software Development :: Libraries
Classifier: Topic :: Software Development :: Libraries :: Python Modules
Classifier: Topic :: Software Development :: Libraries :: Application Frameworks
Classifier: Topic :: Software Development :: Version Control :: Git
Classifier: Topic :: System :: Archiving :: Packaging
Classifier: Topic :: System :: Installation/Setup
Classifier: Topic :: System :: Software Distribution
Classifier: Programming Language :: Python :: 3 :: Only
Classifier: Programming Language :: Python :: 3.7
Classifier: Programming Language :: Python :: 3.8
Classifier: Programming Language :: Python :: 3.9
Classifier: Programming Language :: Python :: 3.10
Classifier: Programming Language :: Python :: 3.11
Classifier: Programming Language :: Python :: 3.12
Requires-Python: <4.0,>=3.11
License-File: LICENSE
Requires-Dist: poetry-core<3,>=1.8.1
Requires-Dist: docker>=7.1.0
Requires-Dist: requests>=2.32.2
Requires-Dist: python-dotenv>=1.0.1
Dynamic: license-file
